setup.py
tcp_libra.egg-info/PKG-INFO
tcp_libra.egg-info/SOURCES.txt
tcp_libra.egg-info/dependency_links.txt
tcp_libra.egg-info/entry_points.txt
tcp_libra.egg-info/not-zip-safe
tcp_libra.egg-info/requires.txt
tcp_libra.egg-info/top_level.txt
tcplibra/__init__.py
tcplibra/api.py
tcplibra/controller.py
tcplibra/handlers.py
tcplibra/models.py
tcplibra/server.py
tcplibra/session.py