Metadata-Version: 1.0
Name: tcp-libra
Version: 0.1.0
Summary: The simple tcp load balancer written in tornado
Home-page: https://github.com/wpjunior/tcplibra.git
Author: Wilson Junior
Author-email: wilsonpjunior@gmail.com
License: MIT
Keywords: tcp load balancer
Platform: UNKNOWN
